setup.py
Marchines/AdaBoost.py
Marchines/Apriori.py
Marchines/C45.py
Marchines/CART.py
Marchines/KMean.py
Marchines/Logistic.py
Marchines/NB.py
Marchines/SVM.py
Marchines/__init__.py
Marchines/kNN.py
Marchines/regTrees.py
Marchines.egg-info/PKG-INFO
Marchines.egg-info/SOURCES.txt
Marchines.egg-info/dependency_links.txt
Marchines.egg-info/top_level.txt