Metadata-Version: 1.1
Name: Marchines
Version: 1.0.9
Summary: Marchines
Home-page: https://gitee.com/madeitcwang/Machine_Learing_in_Action
Author: madeitcwang
Author-email: 1321711107@qq.com
License: BSD License
Platform: all
Classifier: Development Status :: 4 - Beta
Classifier: Operating System :: OS Independent
Classifier: Intended Audience :: Developers
Classifier: License :: OSI Approved :: BSD License
Classifier: Programming Language :: Python :: 3.3
Classifier: Programming Language :: Python :: 3.4
Classifier: Programming Language :: Python :: 3.5
Classifier: Programming Language :: Python :: 3.6
Classifier: Topic :: Software Development :: Libraries
